{
  "$schema": "https://schema.management.basedi.io/schemas/2019-10-05/deploymentTemplate.json#",
  "contentVersion": "1.0.0.0",
  "baseDI_NerdyGroupAffiliates_DynamicWebsite_MainProfile": {
    "value": {
      "baseDIInstructions": {
        "configuration": [
          {
            "key_1": "Servers",
            "values_2": [
              {
                "key_2_1": "Server_1_0",
                "values_2_2": [
                  {
                    "key_2_2_1": "NodeJS",
                    "values_2_2_2": [
                      {
                        "_2_2_2_1_serverInformationSetupDetails": {
                          "searchkey": "SetupDetails_Servers_Server_1_0_NodeJS_2_2_2_1_serverInformationSetupDetails",
                          "type": "array",
                          "value": [
                            {
                              "_2_2_2_1_1_serverInformationSetupItem": {
                                "searchkey": "SetupItem_SetBuyer_ProductLaunching_Software_TransportEnvironment",
                                "type": "object",
                                "value": {
                                  "SetupItemRowID": "1",
                                  "SetupItemEnvironmentName": "Local",
                                  "SetupItemEnvironmentPort": "8912",
                                  "SetupItemEnvironmentDomainName": "http://localhost",
                                  "SetupItemEnvironmentClient": {
                                    "SetupItemBuildItemClientPath": "wwwroot/Client/Build",
                                    "SetupItemDataPath": "wwwroot/Client/Data",
                                    "SetupItemDocumentPath": "wwwroot/Client/Documents",
                                    "SetupItemFontPath": "wwwroot/Client/Fonts",
                                    "SetupItemImagePath": "wwwroot/Client/Images",
                                    "SetupItemScriptPath": "wwwroot/Client/Scripts"
                                  },
                                  "SetupItemEnvironmentServer": {
                                    "SetupItemTransportItemRoutesGET": [
                                      {
                                        "SetupItemTransportItemRoute": {
                                          "ControllerRoutes": [ "/", "/Home" ],
                                          "ControllerName": "Director_Of_WebDevelopment_Chapter_12_3_Page_1_ReadHomeScreenForAll_Handler_1_0",
                                          "ModelDataLocalObject": {},
                                          "ModelDataLocalParameter": "Director_Of_WebDevelopment_Chapter_12_3_Page_1_ReadHomeScreenForAll_Handler_1_0-P1_0",
                                          "ModelDataRemote": {}
                                        }
                                      },
                                      {
                                        "SetupItemTransportItemRoute": {
                                          "ControllerRoutes": [ "/Blog", "/Podcast" ],
                                          "ControllerName": "Director_Of_WebDevelopment_Chapter_12_3_Page_2_ReadPresalesScreenForAll_Handler_1_0",
                                          "ModelDataLocalObject": {},
                                          "ModelDataLocalParameter": "Director_Of_WebDevelopment_Chapter_12_3_Page_2_ReadPresalesScreenForAll_Handler_1_0-P1_0",
                                          "ModelDataRemote": {}
                                        }
                                      },
                                      {
                                        "SetupItemTransportItemRoute": {
                                          "ControllerRoutes": [ "/Optin" ],
                                          "ControllerName": "Director_Of_WebDevelopment_Chapter_12_3_Page_3_ReadOptinScreenForAll_Handler_1_0",
                                          "ModelDataLocalObject": {},
                                          "ModelDataLocalParameter": "Director_Of_WebDevelopment_Chapter_12_3_Page_3_ReadOptinScreenForAll_Handler_1_0-P1_0",
                                          "ModelDataRemote": {}
                                        }
                                      },
                                      {
                                        "SetupItemTransportItemRoute": {
                                          "ControllerRoutes": [ "/ThankYou" ],
                                          "ControllerName": "Director_Of_WebDevelopment_Chapter_12_3_Page_4_ReadThankYouScreenForAll_Handler_1_0",
                                          "ModelDataLocalObject": {},
                                          "ModelDataLocalParameter": "Director_Of_WebDevelopment_Chapter_12_3_Page_4_ReadThankYouScreenForAll_Handler_1_0-P1_0",
                                          "ModelDataRemote": {}
                                        }
                                      },
                                      {
                                        "SetupItemTransportItemRoute": {
                                          "ControllerRoutes": [ "/Sales" ],
                                          "ControllerName": "Director_Of_WebDevelopment_Chapter_12_3_Page_5_ReadSalesScreenForAll_Handler_1_0",
                                          "ModelDataLocalObject": {},
                                          "ModelDataLocalParameter": "Director_Of_WebDevelopment_Chapter_12_3_Page_5_ReadSalesScreenForAll_Handler_1_0-P1_0",
                                          "ModelDataRemote": {}
                                        }
                                      },
                                      {
                                        "SetupItemTransportItemRoute": {
                                          "ControllerRoutes": [ "/OrderForm" ],
                                          "ControllerName": "Director_Of_WebDevelopment_Chapter_12_3_Page_6_ReadOrderFormScreenForAll_Handler_1_0",
                                          "ModelDataLocalObject": {},
                                          "ModelDataLocalParameter": "Director_Of_WebDevelopment_Chapter_12_3_Page_6_ReadOrderFormScreenForAll_Handler_1_0-P1_0",
                                          "ModelDataRemote": {}
                                        }
                                      },
                                      {
                                        "SetupItemTransportItemRoute": {
                                          "ControllerRoutes": [ "/OTO" ],
                                          "ControllerName": "Director_Of_WebDevelopment_Chapter_12_3_Page_7_ReadOTOScreenForAll_Handler_1_0",
                                          "ModelDataLocalObject": {},
                                          "ModelDataLocalParameter": "Director_Of_WebDevelopment_Chapter_12_3_Page_7_ReadOTOScreenForAll_Handler_1_0-P1_0",
                                          "ModelDataRemote": {}
                                        }
                                      },
                                      {
                                        "SetupItemTransportItemRoute": {
                                          "ControllerRoutes": [ "/Webinar" ],
                                          "ControllerName": "Director_Of_WebDevelopment_Chapter_12_3_Page_8_ReadWebinarScreenForAll_Handler_1_0",
                                          "ModelDataLocalObject": {},
                                          "ModelDataLocalParameter": "Director_Of_WebDevelopment_Chapter_12_3_Page_8_ReadWebinarScreenForAll_Handler_1_0-P1_0",
                                          "ModelDataRemote": {}
                                        }
                                      },
                                      {
                                        "SetupItemTransportItemRoute": {
                                          "ControllerRoutes": [ "/Membership" ],
                                          "ControllerName": "Director_Of_WebDevelopment_Chapter_12_3_Page_9_ReadMembershipScreenForAll_Handler_1_0",
                                          "ModelDataLocalObject": {},
                                          "ModelDataLocalParameter": "Director_Of_WebDevelopment_Chapter_12_3_Page_9_ReadMembershipScreenForAll_Handler_1_0-P1_0",
                                          "ModelDataRemote": {}
                                        }
                                      },
                                      {
                                        "SetupItemTransportItemRoute": {
                                          "ControllerRoutes": [ "/Affiliate" ],
                                          "ControllerName": "Director_Of_WebDevelopment_Chapter_12_3_Page_10_ReadAffiliateScreenForAll_Handler_1_0",
                                          "ModelDataLocalObject": {},
                                          "ModelDataLocalParameter": "Director_Of_WebDevelopment_Chapter_12_3_Page_10_ReadAffiliateScreenForAll_Handler_1_0-P1_0",
                                          "ModelDataRemote": {}
                                        }
                                      },
                                      {
                                        "SetupItemTransportItemRoute": {
                                          "ControllerRoutes": [ "/How-To" ],
                                          "ControllerName": "Director_Of_WebDevelopment_Chapter_12_3_Page_11_ReadOtherScreenForAll_Handler_1_0",
                                          "ModelDataLocalObject": {},
                                          "ModelDataLocalParameter": "Director_Of_WebDevelopment_Chapter_12_3_Page_11_ReadOtherScreenForAll_Handler_1_0-P1_0",
                                          "ModelDataRemote": {}
                                        }
                                      },
                                      {
                                        "SetupItemTransportItemRoute": {
                                          "ControllerRoutes": [ "/OrganizeDigitalAssets", "/TransportDigitalAssets" ],
                                          "ControllerName": "Experience_The_Movement_OfTheAssets_Content_12_2_1_0",
                                          "ModelDataLocalObject": {},
                                          "ModelDataLocalParameter": "Experience_The_Movement_OfTheAssets_Content_12_2_1_0-P1_0",
                                          "ModelDataRemote": {}
                                        }
                                      },
                                      {
                                        "SetupItemTransportItemRoute": {
                                          "ControllerRoutes": [ "/Components", "/3rdParty" ],
                                          "ControllerName": "Director_Of_WebDevelopment_Chapter_12_3_Page_12_ReadAdvancedScreenForAll_Handler_1_0",
                                          "ModelDataLocalObject": {},
                                          "ModelDataLocalParameter": "Director_Of_WebDevelopment_Chapter_12_3_Page_12_ReadAdvancedScreenForAll_Handler_1_0-P1_0",
                                          "ModelDataRemote": {}
                                        }
                                      },
                                      {
                                        "SetupItemTransportItemRoute": {
                                          "ControllerRoutes": [ "/Advertising" ],
                                          "ControllerName": "Director_Of_Advertising_Chapter_1_1_Page_2_CreateWhereAPersonBecameAwareOfTopic_Handler_1_0",
                                          "ModelDataLocalObject": {},
                                          "ModelDataLocalParameter": "Director_Of_Advertising_Chapter_1_1_Page_2_CreateWhereAPersonBecameAwareOfTopic_Handler_1_0-P1_4_1_1",
                                          "ModelDataRemote": {}
                                        }
                                      },
                                      {
                                        "SetupItemTransportItemRoute": {
                                          "ControllerRoutes": [ "/AuthRequest", "/AuthResponse" ],
                                          "ControllerName": "Director_Of_Security_Chapter_12_5_Page_1_ReadAuthenticationForAll_Handler_1_0",
                                          "ModelDataLocalObject": {},
                                          "ModelDataLocalParameter": "Director_Of_Security_Chapter_12_5_Page_1_ReadAuthenticationForAll_Handler_1_0-P1_0",
                                          "ModelDataRemote": {}
                                        }
                                      }
                                    ]
                                  }
                                }
                              }
                            }
                          ]
                        }
                      }
                    ]
                  }
                ]
              }
            ],
            "type_3": "object",
            "buzzWords_4": "***OPTIONAL***, NodeJS, WebAPI",
            "extraKeyValuePairs_5": [
              {}
            ]
          }
        ],
        "presentation": [ {} ],
        "business": [
          {
            "key_1": "Request",
            "values_2": [
              {
                "key_2_1": "Request_1_0",
                "values_2_2": [
                  {
                    "key_2_2_1": "Server",
                    "values_2_2_2": [
                      {
                        "_2_2_2_1_functionInformationEventCallStackDetails": {
                          "searchkey": "HTMLSourceCode_SetImplementer_ProductCreation_WebDevelopment_RequestHandler",
                          "type": "array",
                          "value": [
                            {
                              "_2_2_2_1_1_functionInformationEventCallStackItem": {
                                "searchkey": "SetImplementer_ProductCreation_Software_BusinessFuction",
                                "type": "object",
                                "value": {
                                  "EventCallStackItemRowID": "1",
                                  "EventCallStackItems": [
                                    {
                                      "Notes": "Web Server",
                                      "Events": [
                                        {
                                          "functionsEnabled": "true"
                                        },
                                        {
                                          "functionEvent": "onload",
                                          "functionName": "Experience_The_Hear_OfTheAPIServer_Message_12_3_1_0",
                                          "functionParameters": [
                                            {
                                              "parameterName": "",
                                              "parameterTypeScriptDataType": "",
                                              "parameterDefaultValue": ""
                                            }
                                          ]
                                        }
                                      ]
                                    }
                                  ]
                                }
                              }
                            }
                          ]
                        }
                      }
                    ]
                  }
                ]
              }
            ],
            "type_3": "object",
            "buzzWords_4": "***REQUIRED***, Functions, Methods, Business Logic",
            "extraKeyValuePairs_5": []
          }
        ],
        "data": [
          {
            "key_1": "CachedDataSets",
            "values_2": [
              {
                "key_2_1": "CachedDataSet_1_0",
                "values_2_2": [
                  {
                    "key_2_2_1": "CachedDataSet",
                    "values_2_2_2": [
                      {
                        "_2_2_2_1_cachedDataSetInformationDataDetails": {
                          "searchkey": "Cache_DataSet_1_0_DataSet_2_2_2_1_DataSetInformationDataDetails",
                          "type": "array",
                          "value": [
                            {
                              "_2_2_2_1_1_cachedDataSetInformationDataItem": {
                                "searchkey": "SetAdministrator_Management_StrategicPlanning_AccessShelfLocations",
                                "type": "object",
                                "value": {
                                  "DataItems": [
                                    {
                                      "Key": "ORG",
                                      "Value": "1. Organize",
                                      "Description": "Productivity",
                                      "AccountOwner": "",
                                      "CorporateBrandCode": ""
                                    },
                                    {
                                      "Key": "TEA",
                                      "Value": "2. Teach",
                                      "Description": "Branding",
                                      "AccountOwner": "",
                                      "CorporateBrandCode": ""
                                    },
                                    {
                                      "Key": "REC",
                                      "Value": "3. Recruit",
                                      "Description": "Productivity",
                                      "AccountOwner": "",
                                      "CorporateBrandCode": ""
                                    },
                                    {
                                      "Key": "AGR",
                                      "Value": "4. Agree",
                                      "Description": "Productivity",
                                      "AccountOwner": ""
                                    },
                                    {
                                      "Key": "EXE",
                                      "Value": "5. Execute",
                                      "Description": "Productivity",
                                      "AccountOwner": "",
                                      "CorporateBrandCode": ""
                                    },
                                    {
                                      "Key": "BRA",
                                      "Value": "6. Brand",
                                      "Description": "Branding",
                                      "AccountOwner": "",
                                      "CorporateBrandCode": ""
                                    },
                                    {
                                      "Key": "LAU",
                                      "Value": "7. Launch",
                                      "Description": "Branding",
                                      "AccountOwner": "",
                                      "CorporateBrandCode": ""
                                    },
                                    {
                                      "Key": "LEA",
                                      "Value": "8. Learn",
                                      "Description": "Productivity",
                                      "AccountOwner": ""
                                    },
                                    {
                                      "Key": "IMP",
                                      "Value": "9. Improve",
                                      "Description": "Productivity",
                                      "AccountOwner": "",
                                      "CorporateBrandCode": ""
                                    },
                                    {
                                      "Key": "AUT",
                                      "Value": "10. Automate",
                                      "Description": "Productivity",
                                      "AccountOwner": "",
                                      "CorporateBrandCode": ""
                                    }
                                  ]
                                }
                              }
                            },
                            {
                              "_2_2_2_1_2_cachedDataSetInformationDataItem": {
                                "searchkey": "SetAdministrator_Management_StrategicPlanning_AccessShelfLocationsTestValues",
                                "type": "object",
                                "value": {
                                  "DataItemTest": [
                                    {
                                      "ASLC": "RTG-BRA-LAU-1_2_H-ADV-2_3_K_1"
                                    }
                                  ]
                                }
                              }
                            },
                            {
                              "_2_2_2_1_3_cachedDataSetInformationDataItem": {
                                "searchkey": "SetAdministrator_Management_StrategicPlanning_AccessShelfLocationsOrganizations",
                                "type": "object",
                                "value": {
                                  "DataItems": [
                                    {
                                      "Key": "1",
                                      "Value": "NerdyGroup",
                                      "Description": "Management",
                                      "AccountOwner": "",
                                      "CorporateBrandCode": ""
                                    },
                                    {
                                      "Key": "1-1-H",
                                      "Value": "Supplier Project",
                                      "Description": "Management",
                                      "AccountOwner": "",
                                      "CorporateBrandCode": ""
                                    },
                                    {
                                      "Key": "1-2-H",
                                      "Value": "Society Influencers",
                                      "Description": "Management",
                                      "AccountOwner": "",
                                      "CorporateBrandCode": ""
                                    },
                                    {
                                      "Key": "1-2-K-1",
                                      "Value": "Community6",
                                      "Description": "Management",
                                      "AccountOwner": "",
                                      "CorporateBrandCode": ""
                                    },
                                    {
                                      "Key": "1-2-K-1-2",
                                      "Value": "OutWith6",
                                      "Description": "Management",
                                      "AccountOwner": "",
                                      "CorporateBrandCode": ""
                                    },
                                    {
                                      "Key": "1-2-K-1-3",
                                      "Value": "Uncensored6",
                                      "Description": "Management",
                                      "AccountOwner": "",
                                      "CorporateBrandCode": ""
                                    },
                                    {
                                      "Key": "1-2-H-2",
                                      "Value": "NerdyGroup Publishing",
                                      "Description": "Management",
                                      "AccountOwner": "",
                                      "CorporateBrandCode": ""
                                    },
                                    {
                                      "Key": "1-2-H-3",
                                      "Value": "Ageless Juicing Challenge",
                                      "Description": "Management",
                                      "AccountOwner": "",
                                      "CorporateBrandCode": ""
                                    },
                                    {
                                      "Key": "1-2-H-3-1",
                                      "Value": "Ageless Organifi",
                                      "Description": "Friendship",
                                      "AccountOwner": "",
                                      "CorporateBrandCode": ""
                                    },
                                    {
                                      "Key": "1-3-H",
                                      "Value": "Society Winners",
                                      "Description": "Management",
                                      "AccountOwner": "",
                                      "CorporateBrandCode": ""
                                    },
                                    {
                                      "Key": "1-4-H",
                                      "Value": "Society Joint Ventures",
                                      "Description": "Management",
                                      "AccountOwner": "",
                                      "CorporateBrandCode": ""
                                    },
                                    {
                                      "Key": "1-4-H-1",
                                      "Value": "Funnel Formations",
                                      "Description": "Organization",
                                      "AccountOwner": "",
                                      "CorporateBrandCode": ""
                                    },
                                    {
                                      "Key": "1-4-H-1-1",
                                      "Value": "Uncensored Funnels",
                                      "Description": "Management",
                                      "AccountOwner": "",
                                      "CorporateBrandCode": ""
                                    },
                                    {
                                      "Key": "1-4-H-2",
                                      "Value": "Amazon Platform",
                                      "Description": "Friendship",
                                      "AccountOwner": "",
                                      "CorporateBrandCode": ""
                                    },
                                    {
                                      "Key": "1-5-G",
                                      "Value": "BaseDI Open Source",
                                      "Description": "Management",
                                      "AccountOwner": "",
                                      "CorporateBrandCode": ""
                                    },
                                    {
                                      "Key": "1-6-F",
                                      "Value": "Tibbix Automation Software",
                                      "Description": "Management",
                                      "AccountOwner": "",
                                      "CorporateBrandCode": ""
                                    },
                                    {
                                      "Key": "2",
                                      "Value": "RMP",
                                      "Description": "Management",
                                      "AccountOwner": "",
                                      "CorporateBrandCode": ""
                                    },
                                    {
                                      "Key": "2-1-J",
                                      "Value": "Stuff Wars",
                                      "Description": "Management",
                                      "AccountOwner": "",
                                      "CorporateBrandCode": ""
                                    },
                                    {
                                      "Key": "2-1-J-1",
                                      "Value": "Stronger Deals",
                                      "Description": "Management",
                                      "AccountOwner": "",
                                      "CorporateBrandCode": ""
                                    },
                                    {
                                      "Key": "2-1-J-1-1",
                                      "Value": "GiftShop6",
                                      "Description": "Management",
                                      "AccountOwner": "",
                                      "CorporateBrandCode": ""
                                    },
                                    {
                                      "Key": "2-1-J-1-2",
                                      "Value": "Amazon",
                                      "Description": "Friendship",
                                      "AccountOwner": "",
                                      "CorporateBrandCode": ""
                                    },
                                    {
                                      "Key": "2-1-J-2",
                                      "Value": "Time Oppression",
                                      "Description": "Management",
                                      "AccountOwner": "",
                                      "CorporateBrandCode": ""
                                    },
                                    {
                                      "Key": "2-1-J-3",
                                      "Value": "Society Decisions",
                                      "Description": "Management",
                                      "AccountOwner": "",
                                      "CorporateBrandCode": ""
                                    },
                                    {
                                      "Key": "2-1-J-3-1",
                                      "Value": "AttractDS",
                                      "Description": "Management",
                                      "AccountOwner": "",
                                      "CorporateBrandCode": ""
                                    },
                                    {
                                      "Key": "2-1-J-3-2",
                                      "Value": "ChristianDS",
                                      "Description": "Management",
                                      "AccountOwner": "",
                                      "CorporateBrandCode": ""
                                    },
                                    {
                                      "Key": "2-1-J-3-3",
                                      "Value": "DatingDS",
                                      "Description": "Management",
                                      "AccountOwner": "",
                                      "CorporateBrandCode": ""
                                    },
                                    {
                                      "Key": "2-1-J-3-4",
                                      "Value": "DemocratsDS",
                                      "Description": "Management",
                                      "AccountOwner": "",
                                      "CorporateBrandCode": ""
                                    },
                                    {
                                      "Key": "2-1-J-3-5",
                                      "Value": "FitnessDS",
                                      "Description": "Management",
                                      "AccountOwner": "",
                                      "CorporateBrandCode": ""
                                    },
                                    {
                                      "Key": "2-1-J-3-6",
                                      "Value": "LGBTDS",
                                      "Description": "Management",
                                      "AccountOwner": "",
                                      "CorporateBrandCode": ""
                                    },
                                    {
                                      "Key": "2-1-J-3-7",
                                      "Value": "MuslimDS",
                                      "Description": "Management",
                                      "AccountOwner": "",
                                      "CorporateBrandCode": ""
                                    },
                                    {
                                      "Key": "2-1-J-3-8",
                                      "Value": "RecruiterDS",
                                      "Description": "Management",
                                      "AccountOwner": "",
                                      "CorporateBrandCode": ""
                                    },
                                    {
                                      "Key": "2-1-J-3-9",
                                      "Value": "RepublicanDS",
                                      "Description": "Management",
                                      "AccountOwner": "",
                                      "CorporateBrandCode": ""
                                    },
                                    {
                                      "Key": "2-1-J-3-10",
                                      "Value": "WealthDS",
                                      "Description": "Management",
                                      "AccountOwner": "",
                                      "CorporateBrandCode": ""
                                    },
                                    {
                                      "Key": "2-1-J-3-11",
                                      "Value": "WellnessDS",
                                      "Description": "Management",
                                      "AccountOwner": "",
                                      "CorporateBrandCode": ""
                                    },
                                    {
                                      "Key": "2-1-J-3-12",
                                      "Value": "6Profile",
                                      "Description": "Management",
                                      "AccountOwner": "",
                                      "CorporateBrandCode": ""
                                    },
                                    {
                                      "Key": "2-2-F",
                                      "Value": "Sketchy Content",
                                      "Description": "Management",
                                      "AccountOwner": "",
                                      "CorporateBrandCode": ""
                                    },
                                    {
                                      "Key": "2-3-K",
                                      "Value": "Webbie Ads",
                                      "Description": "Management",
                                      "AccountOwner": "",
                                      "CorporateBrandCode": ""
                                    },
                                    {
                                      "Key": "2-3-K-1",
                                      "Value": "Instagram",
                                      "Description": "Friendship",
                                      "AccountOwner": "",
                                      "CorporateBrandCode": ""
                                    },
                                    {
                                      "Key": "2-3-K-2",
                                      "Value": "Facebook",
                                      "Description": "Friendship",
                                      "AccountOwner": "",
                                      "CorporateBrandCode": ""
                                    },
                                    {
                                      "Key": "2-3-K-3",
                                      "Value": "YouTube",
                                      "Description": "Friendship",
                                      "AccountOwner": "",
                                      "CorporateBrandCode": ""
                                    },
                                    {
                                      "Key": "2-3-K-4",
                                      "Value": "LinkedIn",
                                      "Description": "Friendship",
                                      "AccountOwner": "",
                                      "CorporateBrandCode": ""
                                    },
                                    {
                                      "Key": "2-4-G",
                                      "Value": "Company Raiders",
                                      "Description": "Management",
                                      "AccountOwner": "",
                                      "CorporateBrandCode": ""
                                    },
                                    {
                                      "Key": "2-4-G-1",
                                      "Value": "LifeIs6",
                                      "Description": "Management",
                                      "AccountOwner": "",
                                      "CorporateBrandCode": ""
                                    },
                                    {
                                      "Key": "2-4-G-2",
                                      "Value": "QuotesFrom6",
                                      "Description": "Management",
                                      "AccountOwner": "",
                                      "CorporateBrandCode": ""
                                    },
                                    {
                                      "Key": "2-5-G",
                                      "Value": "Richardson Reality Properties",
                                      "Description": "Management",
                                      "AccountOwner": "",
                                      "CorporateBrandCode": ""
                                    },
                                    {
                                      "Key": "3",
                                      "Value": "Agency Jace",
                                      "Description": "Management",
                                      "AccountOwner": "",
                                      "CorporateBrandCode": ""
                                    },
                                    {
                                      "Key": "3-1-H",
                                      "Value": "Society Producers",
                                      "Description": "Management",
                                      "AccountOwner": "",
                                      "CorporateBrandCode": ""
                                    },
                                    {
                                      "Key": "3-2-G",
                                      "Value": "Society Business Consulting",
                                      "Description": "Management",
                                      "AccountOwner": "",
                                      "CorporateBrandCode": ""
                                    },
                                    {
                                      "Key": "3-3-G",
                                      "Value": "Society Recruiters",
                                      "Description": "Management",
                                      "AccountOwner": "",
                                      "CorporateBrandCode": ""
                                    }
                                  ]
                                }
                              }
                            },
                            {
                              "_2_2_2_1_4_cachedDataSetInformationDataItem": {
                                "searchkey": "SetAdministrator_Management_StrategicPlanning_AccessShelfLocationsPeople",
                                "type": "object",
                                "value": {
                                  "DataItems": [
                                    {
                                      "Key": "MR1",
                                      "Value": "Mark Richardson",
                                      "Description": "Internal",
                                      "AccountOwner": [
                                        {
                                          "EmailAccounts": {
                                            "Value": "mark@nerdygroupaffiliates.com",
                                            "SubAccounts": [
                                              {
                                                "Value": "BusinessGuy1979@gmail.com"
                                              },
                                              {
                                                "Value": "thephantom1979@gmail.com"
                                              }
                                            ]
                                          }
                                        }
                                      ],
                                      "CorporateBrandCode": ""
                                    },
                                    {
                                      "Key": "SR1",
                                      "Value": "Shaunna Richardson",
                                      "Description": "Internal",
                                      "AccountOwner": [
                                        {
                                          "EmailAccounts": {
                                            "Value": "shaunna@richardsonmediaproperties.com",
                                            "SubAccounts": [
                                              {
                                                "Value": "shaunna_29@hotmail.com"
                                              }
                                            ]
                                          }
                                        }
                                      ],
                                      "CorporateBrandCode": ""
                                    },
                                    {
                                      "Key": "TR1",
                                      "Value": "Timothy Richardson",
                                      "Description": "Person",
                                      "AccountOwner": [
                                        {
                                          "EmailAccounts": {
                                            "Value": "tim@agencyjace.com",
                                            "SubAccounts": [
                                              {
                                                "Value": "trichardson01@gmail.com"
                                              }
                                            ]
                                          }
                                        }
                                      ],
                                      "CorporateBrandCode": ""
                                    },
                                    {
                                      "Key": "AD1",
                                      "Value": "Andrew Durham",
                                      "Description": "Internal",
                                      "AccountOwner": [
                                        {
                                          "EmailAccounts": {
                                            "Value": "Andrew@agelessandrew.com",
                                            "SubAccounts": [
                                              {
                                                "Value": "agelessandrew@gmail.com"
                                              }
                                            ]
                                          }
                                        }
                                      ],
                                      "CorporateBrandCode": ""
                                    },
                                    {
                                      "Key": "RR1",
                                      "Value": "Ross Robbins",
                                      "Description": "Internal",
                                      "AccountOwner": [
                                        {
                                          "EmailAccounts": {
                                            "Value": "ross@funnelformations.com",
                                            "SubAccounts": [
                                              {
                                                "Value": "rossdaboss1996@gmail.com"
                                              }
                                            ]
                                          }
                                        }
                                      ],
                                      "CorporateBrandCode": ""
                                    },
                                    {
                                      "Key": "AW1",
                                      "Value": "Andrew Wong",
                                      "Description": "Person",
                                      "AccountOwner": [
                                        {
                                          "EmailAccounts": {
                                            "Value": "",
                                            "SubAccounts": [
                                              {
                                                "Value": ""
                                              }
                                            ]
                                          }
                                        }
                                      ],
                                      "CorporateBrandCode": ""
                                    },
                                    {
                                      "Key": "MW1",
                                      "Value": "Mubasher Wajid",
                                      "Description": "External",
                                      "AccountOwner": [
                                        {
                                          "EmailAccounts": {
                                            "Value": "mubasher043@gmail.com",
                                            "SubAccounts": [
                                              {
                                                "Value": ""
                                              }
                                            ]
                                          }
                                        }
                                      ],
                                      "CorporateBrandCode": ""
                                    },
                                    {
                                      "Key": "KG1.",
                                      "Value": "Kishor Gujar",
                                      "Description": "External",
                                      "AccountOwner": [
                                        {
                                          "EmailAccounts": {
                                            "Value": "kishorgujar95@gmail.com",
                                            "SubAccounts": [
                                              {
                                                "Value": ""
                                              }
                                            ]
                                          }
                                        }
                                      ],
                                      "CorporateBrandCode": ""
                                    },
                                    {
                                      "Key": "AH1",
                                      "Value": "Atif Hussain",
                                      "Description": "External",
                                      "AccountOwner": [
                                        {
                                          "EmailAccounts": {
                                            "Value": "atifhussain49@gmail.com",
                                            "SubAccounts": [
                                              {
                                                "Value": ""
                                              }
                                            ]
                                          }
                                        }
                                      ],
                                      "CorporateBrandCode": ""
                                    },
                                    {
                                      "Key": "LR1",
                                      "Value": "Louie Rosero",
                                      "Description": "External",
                                      "AccountOwner": [
                                        {
                                          "EmailAccounts": {
                                            "Value": "roserolouie@gmail.com",
                                            "SubAccounts": [
                                              {
                                                "Value": ""
                                              }
                                            ]
                                          }
                                        }
                                      ],
                                      "CorporateBrandCode": ""
                                    }
                                  ]
                                }
                              }
                            }
                          ]
                        }
                      }
                    ]
                  }
                ]
              }
            ],
            "type_3": "object",
            "buzzWords_4": "***REQUIRED***, LocalFile, LocalDatabase, LocalService, RemoteFile, RemoteDatabase, RemoteService, RemoteServiceVendor",
            "extraKeyValuePairs_5": [
              {}
            ]
          },
          {
            "key_1": "Repositories",
            "values_2": [
              {
                "key_2_1": "Repository_1_0",
                "values_2_2": [
                  {
                    "key_2_2_1": "Repository",
                    "values_2_2_2": [
                      {
                        "_2_2_2_1_repositoryInformationDataDetails": {
                          "searchkey": "Repositories_Repository_1_0_Repository_2_2_2_1_RepositoryInformationDataDetails",
                          "type": "array",
                          "value": [
                            {
                              "_2_2_2_1_1_repositoryInformationDataItem": {
                                "searchkey": "SetImplementer_ProductCreation_Software_Data",
                                "type": "object",
                                "value": {
                                  "DataItemRowID": "1",
                                  "DataItemLocation": "LocalService"
                                }
                              },
                              "_2_2_2_1_2_repositoryInformationDataItem": {
                                "searchkey": "SetImplementer_ProductCreation_Software_DataException",
                                "type": "object",
                                "value": {
                                  "DataItemRowID": "2",
                                  "DataItemLocation": "LocalService"
                                }
                              },
                              "_2_2_2_1_3_repositoryInformationDataItem": {
                                "searchkey": "SetImplementer_ProductCreation_Software_MasterLeaderController",
                                "type": "object",
                                "value": {
                                  "DataItemRowID": "3",
                                  "DataItemLocation": "LocalFile"
                                }
                              }
                            }
                          ]
                        }
                      }
                    ]
                  }
                ]
              }
            ],
            "type_3": "object",
            "buzzWords_4": "***REQUIRED***, LocalFile, LocalDatabase, LocalService, RemoteFile, RemoteDatabase, RemoteService, RemoteServiceVendor",
            "extraKeyValuePairs_5": [
              {}
            ]
          }
        ]
      }
    }
  }
}